<?xml version="1.0" encoding="UTF-8"?>
<GenRun Id="impl_2" LaunchPart="xc7z010clg400-1" LaunchTime="1506741255">
  <File Type="PWROPT-DRC" Name="AHBLITE_SYS_drc_pwropted.rpt"/>
  <File Type="OPT-METHODOLOGY-DRC" Name="AHBLITE_SYS_methodology_drc_opted.rpt"/>
  <File Type="INIT-TIMING" Name="AHBLITE_SYS_timing_summary_init.rpt"/>
  <File Type="ROUTE-PWR-RPX" Name="AHBLITE_SYS_power_routed.rpx"/>
  <File Type="PA-TCL" Name="AHBLITE_SYS.tcl"/>
  <File Type="OPT-HWDEF" Name="AHBLITE_SYS.hwdef"/>
  <File Type="RDI-RDI" Name="AHBLITE_SYS.vdi"/>
  <File Type="OPT-DCP" Name="AHBLITE_SYS_opt.dcp"/>
  <File Type="OPT-DRC" Name="AHBLITE_SYS_drc_opted.rpt"/>
  <File Type="OPT-TIMING" Name="AHBLITE_SYS_timing_summary_opted.rpt"/>
  <File Type="PWROPT-DCP" Name="AHBLITE_SYS_pwropt.dcp"/>
  <File Type="PWROPT-TIMING" Name="AHBLITE_SYS_timing_summary_pwropted.rpt"/>
  <File Type="PLACE-DCP" Name="AHBLITE_SYS_placed.dcp"/>
  <File Type="PLACE-IO" Name="AHBLITE_SYS_io_placed.rpt"/>
  <File Type="PLACE-CLK" Name="AHBLITE_SYS_clock_utilization_placed.rpt"/>
  <File Type="PLACE-UTIL" Name="AHBLITE_SYS_utilization_placed.rpt"/>
  <File Type="PLACE-UTIL-PB" Name="AHBLITE_SYS_utilization_placed.pb"/>
  <File Type="PLACE-CTRL" Name="AHBLITE_SYS_control_sets_placed.rpt"/>
  <File Type="PLACE-SIMILARITY" Name="AHBLITE_SYS_incremental_reuse_placed.rpt"/>
  <File Type="PLACE-PRE-SIMILARITY" Name="AHBLITE_SYS_incremental_reuse_pre_placed.rpt"/>
  <File Type="PLACE-TIMING" Name="AHBLITE_SYS_timing_summary_placed.rpt"/>
  <File Type="POSTPLACE-PWROPT-DCP" Name="AHBLITE_SYS_postplace_pwropt.dcp"/>
  <File Type="POSTPLACE-PWROPT-TIMING" Name="AHBLITE_SYS_timing_summary_postplace_pwropted.rpt"/>
  <File Type="PHYSOPT-DCP" Name="AHBLITE_SYS_physopt.dcp"/>
  <File Type="PHYSOPT-DRC" Name="AHBLITE_SYS_drc_physopted.rpt"/>
  <File Type="PHYSOPT-TIMING" Name="AHBLITE_SYS_timing_summary_physopted.rpt"/>
  <File Type="ROUTE-ERROR-DCP" Name="AHBLITE_SYS_routed_error.dcp"/>
  <File Type="ROUTE-DCP" Name="AHBLITE_SYS_routed.dcp"/>
  <File Type="ROUTE-BLACKBOX-DCP" Name="AHBLITE_SYS_routed_bb.dcp"/>
  <File Type="ROUTE-DRC" Name="AHBLITE_SYS_drc_routed.rpt"/>
  <File Type="ROUTE-DRC-PB" Name="AHBLITE_SYS_drc_routed.pb"/>
  <File Type="BG-BIN" Name="AHBLITE_SYS.bin"/>
  <File Type="ROUTE-DRC-RPX" Name="AHBLITE_SYS_drc_routed.rpx"/>
  <File Type="BG-DRC" Name="AHBLITE_SYS.drc"/>
  <File Type="ROUTE-METHODOLOGY-DRC" Name="AHBLITE_SYS_methodology_drc_routed.rpt"/>
  <File Type="BITSTR-MSK" Name="AHBLITE_SYS.msk"/>
  <File Type="ROUTE-METHODOLOGY-DRC-RPX" Name="AHBLITE_SYS_methodology_drc_routed.rpx"/>
  <File Type="BG-BGN" Name="AHBLITE_SYS.bgn"/>
  <File Type="ROUTE-METHODOLOGY-DRC-PB" Name="AHBLITE_SYS_methodology_drc_routed.pb"/>
  <File Type="ROUTE-PWR" Name="AHBLITE_SYS_power_routed.rpt"/>
  <File Type="ROUTE-PWR-SUM" Name="AHBLITE_SYS_power_summary_routed.pb"/>
  <File Type="ROUTE-STATUS" Name="AHBLITE_SYS_route_status.rpt"/>
  <File Type="ROUTE-STATUS-PB" Name="AHBLITE_SYS_route_status.pb"/>
  <File Type="ROUTE-TIMINGSUMMARY" Name="AHBLITE_SYS_timing_summary_routed.rpt"/>
  <File Type="ROUTE-TIMING-PB" Name="AHBLITE_SYS_timing_summary_routed.pb"/>
  <File Type="ROUTE-TIMING-RPX" Name="AHBLITE_SYS_timing_summary_routed.rpx"/>
  <File Type="ROUTE-SIMILARITY" Name="AHBLITE_SYS_incremental_reuse_routed.rpt"/>
  <File Type="ROUTE-CLK" Name="AHBLITE_SYS_clock_utilization_routed.rpt"/>
  <File Type="POSTROUTE-PHYSOPT-DCP" Name="AHBLITE_SYS_postroute_physopt.dcp"/>
  <File Type="POSTROUTE-PHYSOPT-BLACKBOX-DCP" Name="AHBLITE_SYS_postroute_physopt_bb.dcp"/>
  <File Type="POSTROUTE-PHYSOPT-TIMING" Name="AHBLITE_SYS_timing_summary_postroute_physopted.rpt"/>
  <File Type="POSTROUTE-PHYSOPT-TIMING-PB" Name="AHBLITE_SYS_timing_summary_postroute_physopted.pb"/>
  <File Type="POSTROUTE-PHYSOPT-TIMING-RPX" Name="AHBLITE_SYS_timing_summary_postroute_physopted.rpx"/>
  <File Type="BG-BIT" Name="AHBLITE_SYS.bit"/>
  <File Type="BITSTR-RBT" Name="AHBLITE_SYS.rbt"/>
  <File Type="BITSTR-NKY" Name="AHBLITE_SYS.nky"/>
  <File Type="BITSTR-BMM" Name="AHBLITE_SYS_bd.bmm"/>
  <File Type="BITSTR-MMI" Name="AHBLITE_SYS.mmi"/>
  <File Type="BITSTR-SYSDEF" Name="AHBLITE_SYS.sysdef"/>
  <File Type="WBT-USG" Name="usage_statistics_webtalk.html"/>
  <FileSet Name="sources" Type="DesignSrcs" RelSrcDir="$PSRCDIR/sources_1">
    <Filter Type="Srcs"/>
    <File Path="$PSRCDIR/sources_1/ip/ClockDiv_2/ClockDiv.xci">
      <FileInfo>
        <Attr Name="ImportPath" Val="$PPRDIR/../../../../ARMSOC_1.srcs/sources_1/ip/ClockDiv_2/ClockDiv.xci"/>
        <Attr Name="ImportTime" Val="1496774379"/>
        <Attr Name="UsedIn" Val="synthesis"/>
        <Attr Name="UsedIn" Val="implementation"/>
        <Attr Name="UsedIn" Val="simulation"/>
      </FileInfo>
    </File>
    <File Path="$PSRCDIR/sources_1/imports/ARMSOC_1/AHBLITE_SYS.v">
      <FileInfo>
        <Attr Name="ImportPath" Val="$PPRDIR/../../../../../AHBLITE_SYS.v"/>
        <Attr Name="ImportTime" Val="1496668430"/>
        <Attr Name="UsedIn" Val="synthesis"/>
        <Attr Name="UsedIn" Val="implementation"/>
        <Attr Name="UsedIn" Val="simulation"/>
      </FileInfo>
    </File>
    <File Path="$PSRCDIR/sources_1/imports/ARMSOC_1/arm_single.sv">
      <FileInfo>
        <Attr Name="ImportPath" Val="$PPRDIR/../../../../../arm_single.sv"/>
        <Attr Name="ImportTime" Val="1496768406"/>
        <Attr Name="UsedIn" Val="synthesis"/>
        <Attr Name="UsedIn" Val="implementation"/>
        <Attr Name="UsedIn" Val="simulation"/>
      </FileInfo>
    </File>
    <File Path="$PSRCDIR/sources_1/imports/ARMSOC_1/Software/imem.sv">
      <FileInfo>
        <Attr Name="ImportPath" Val="$PPRDIR/../../../../../Software/imem.sv"/>
        <Attr Name="ImportTime" Val="1496955837"/>
        <Attr Name="UsedIn" Val="synthesis"/>
        <Attr Name="UsedIn" Val="implementation"/>
        <Attr Name="UsedIn" Val="simulation"/>
      </FileInfo>
    </File>
    <File Path="$PPRDIR/archive_project_summary.txt"/>
    <File Path="$PSRCDIR/sources_1/imports/Software/ahbrom.sv">
      <FileInfo>
        <Attr Name="ImportPath" Val="$PPRDIR/../Software/ahbrom.sv"/>
        <Attr Name="ImportTime" Val="1498694457"/>
        <Attr Name="UsedIn" Val="synthesis"/>
        <Attr Name="UsedIn" Val="implementation"/>
        <Attr Name="UsedIn" Val="simulation"/>
      </FileInfo>
    </File>
    <Config>
      <Option Name="DesignMode" Val="RTL"/>
      <Option Name="TopModule" Val="AHBLITE_SYS"/>
    </Config>
  </FileSet>
  <FileSet Name="constrs_in" Type="Constrs" RelSrcDir="$PSRCDIR/constrs_1">
    <Filter Type="Constrs"/>
    <File Path="$PPRDIR/../../../ZYBO-master/Resources/XDC/ZYBO_Master.xdc">
      <FileInfo>
        <Attr Name="UsedIn" Val="synthesis"/>
        <Attr Name="UsedIn" Val="implementation"/>
      </FileInfo>
    </File>
    <Config>
      <Option Name="TargetConstrsFile" Val="$PPRDIR/../../../ZYBO-master/Resources/XDC/ZYBO_Master.xdc"/>
      <Option Name="ConstrsType" Val="XDC"/>
    </Config>
  </FileSet>
  <Strategy Version="1" Minor="2">
    <StratHandle Name="Vivado Implementation Defaults" Flow="Vivado Implementation 2016"/>
    <Step Id="init_design"/>
    <Step Id="opt_design"/>
    <Step Id="power_opt_design"/>
    <Step Id="place_design"/>
    <Step Id="post_place_power_opt_design"/>
    <Step Id="phys_opt_design"/>
    <Step Id="route_design"/>
    <Step Id="post_route_phys_opt_design"/>
    <Step Id="write_bitstream"/>
  </Strategy>
</GenRun>
